setup.py
StackingNonlinearTransformations.egg-info/PKG-INFO
StackingNonlinearTransformations.egg-info/SOURCES.txt
StackingNonlinearTransformations.egg-info/dependency_links.txt
StackingNonlinearTransformations.egg-info/top_level.txt
stackingnonlineartransformations/__init__.py
stackingnonlineartransformations/stackingnonlineartransformations.py