Metadata-Version: 2.1
Name: StackingNonlinearTransformations
Version: 0.0.5
Summary: Stacking algorithm optimization 
Home-page: https://gitee.com/caoxinyu123/prostate_cancer_related_research/blob/master/stackingnonlineartransformations.py
Author: caoxinyu
Author-email: 398424191@qqc.om
License: UNKNOWN
Keywords: python,windows,mac,linux
Platform: UNKNOWN
Classifier: Programming Language :: Python :: 3
Classifier: License :: OSI Approved :: MIT License
Classifier: Operating System :: OS Independent
Requires-Python: >=3.6
